{"source": {"id": "cnbc", "name": "CNBC"}, "author": "Maggie Fitzgerald", "title": "A recovery in Nvidia's gaming business will rally the stock 25%, says Evercore", "description": "Evercore ISI raised its price target on Nvidia, betting its gaming segment will send the stock upward.", "url": "https://www.cnbc.com/2019/10/07/nvidias-gaming-business-recovery-will-rally-stock-25percent-says-evercore.html", "urlToImage": "https://image.cnbcfm.com/api/v1/image/105579106-1542381047282gettyimages-618580542.jpeg?v=1570452364", "publishedAt": "2019-10-07T14:16:00Z", "content": "A recovery in Nvidia's gaming business will send the\u00a0stock upward, according to Evercore ISI.\u00a0\r\nThe firm reiterated its outperform rating on the stock and raised its price target to $225 from $185, a 25% upside for the stock."}