{"source": {"id": "cnbc", "name": "CNBC"}, "author": "Reuters", "title": "London police arrest 276 climate change protesters", "description": "London's Metropolitan Police said on Monday it had so far arrested 267 people taking part in demonstrations organized by the climate change protest group Extinction Rebellion.", "url": "https://www.cnbc.com/2019/10/07/london-police-arrest-276-climate-change-protesters.html", "urlToImage": "https://image.cnbcfm.com/api/v1/image/106168568-1570478279129rtx76jcu.jpg?v=1570478351", "publishedAt": "2019-10-07T20:13:00Z", "content": "London's Metropolitan Police said on Monday it had so far arrested 267 people taking part in demonstrations organized by the climate change protest group Extinction Rebellion.\r\nThousands of climate-change protesters took to the streets in cities around the wo\u2026 [+316 chars]"}